{
  "subtitle": "\u09b6\u09bf\u09b6\u09c1 \u0989\u09a8\u09cd\u09a8\u09af\u09bc\u09a8", 
  "uuid": "2b94f1c6ee204bac9e2ff328707c0b85", 
  "language": "ben_BD", 
  "title": "\u09b6\u09bf\u09b6\u09c1 \u0989\u09a8\u09cd\u09a8\u09af\u09bc\u09a8", 
  "image": null, 
  "_version": {
    "package_version": "0.3.3", 
    "language_version": "2.7.6", 
    "language": "python", 
    "language_version_string": "2.7.6 (default, Mar 22 2014, 23:03:41) \n[GCC 4.8.2]", 
    "package": "elastic-git"
  }, 
  "slug": "ChildDevelopmentandEarlyLearning", 
  "source": "5eb7b6c9d98e4cec8aab6735acb4ef08", 
  "position": 3, 
  "image_host": "http://thumbor.unicore.io", 
  "featured_in_navbar": false, 
  "id": null
}